Compiled from "Math.java"
public class com.timelordtty.study.jvm.Math {
  public static final int initData;

  public static com.timelordtty.study.jvm.User user;

  public com.timelordtty.study.jvm.Math();
    Code:
       0: aload_0
       1: invokespecial #1                  // Method java/lang/Object."<init>":()V
       4: return

  public int computer();
    Code:
       0: iconst_1
       1: istore_1
       2: iconst_1
       3: istore_2
       4: iload_1
       5: iload_2
       6: iadd
       7: bipush        10
       9: imul
      10: istore_3
      11: iload_3
      12: ireturn

  public static void main(java.lang.String[]);
    Code:
       0: new           #2                  // class com/timelordtty/study/jvm/Math
       3: dup
       4: invokespecial #3                  // Method "<init>":()V
       7: astore_1
       8: aload_1
       9: invokevirtual #4                  // Method computer:()I
      12: pop
      13: getstatic     #5                  // Field java/lang/System.out:Ljava/io/PrintStream;
      16: ldc           #6                  // String test
      18: invokevirtual #7                  // Method java/io/PrintStream.println:(Ljava/lang/String;)V
      21: return

  static {};
    Code:
       0: new           #8                  // class com/timelordtty/study/jvm/User
       3: dup
       4: invokespecial #9                  // Method com/timelordtty/study/jvm/User."<init>":()V
       7: putstatic     #10                 // Field user:Lcom/timelordtty/study/jvm/User;
      10: return
}
